setup.cfg
setup.py
oyster/__init__.py
oyster/oyster.py
oyster/utils.py
oyster.egg-info/PKG-INFO
oyster.egg-info/SOURCES.txt
oyster.egg-info/dependency_links.txt
oyster.egg-info/not-zip-safe
oyster.egg-info/requires.txt
oyster.egg-info/top_level.txt