Metadata-Version: 1.1
Name: oyster
Version: 0.0.5
Summary: Nothing to see here. Move along.
Home-page: UNKNOWN
Author: Florian Brozek
Author-email: florianbrozek@protonmail.ch
License: UNKNOWN
Platform: UNKNOWN
Classifier: Programming Language :: Python :: 3.5
